{"cameraMode":{"drawMode":0,"name":"Shaded","section":"Shading Mode"},"sceneLighting":true,"audioPlay":false,"sceneViewState":{"showFog":true,"showMaterialUpdate":false,"showSkybox":true,"showFlares":true,"showImageEffects":true,"showParticleSystems":true},"in2DMode":false,"pivot":{"x":-7.0462188720703129,"y":-20.84712028503418,"z":19.39591407775879},"rotation":{"x":-0.4025459587574005,"y":0.11621273308992386,"z":-0.051604416221380237,"w":-0.9065254926681519},"size":41.2164192199707,"orthographic":false}